github_contributor_matcher/__init__.py
github_contributor_matcher/contributor_matcher.py
Github_Contributor_Matcher-0.1.2.dist-info/LICENSE.md
Github_Contributor_Matcher-0.1.2.dist-info/METADATA
Github_Contributor_Matcher-0.1.2.dist-info/WHEEL
Github_Contributor_Matcher-0.1.2.dist-info/entry_points.txt
Github_Contributor_Matcher-0.1.2.dist-info/top_level.txt
Github_Contributor_Matcher-0.1.2.dist-info/RECORD
