Metadata-Version: 2.1
Name: Github-Contributor-Matcher
Version: 0.1.2
Summary: Identify contributors of a repo, given their organization
Home-page: https://github.com/dannyzen/github_contributor_matcher
Author: Dannyzen
Author-email: danny.rosen@gmail.com
License: UNKNOWN
Keywords: github contributor organization matcher repo
Platform: UNKNOWN
Classifier: Programming Language :: Python :: 3
Classifier: License :: OSI Approved :: Apache Software License
Classifier: Operating System :: OS Independent
Requires-Dist: github3.py (==1.2.0)
